LICENSE
MANIFEST.in
README.rst
setup.cfg
setup.py
versioneer.py
artellapipe/__init__.py
artellapipe/libs/__init__.py
artellapipe/libs/drive/__init__.py
artellapipe/libs/drive/__logging__.ini
artellapipe/libs/drive/__version__.py
artellapipe/libs/drive/_version.py
artellapipe/libs/drive/core/__init__.py
artellapipe/libs/drive/core/tracking.py
artellapipe/libs/drive/externals/__init__.py
artellapipe_libs_drive.egg-info/PKG-INFO
artellapipe_libs_drive.egg-info/SOURCES.txt
artellapipe_libs_drive.egg-info/dependency_links.txt
artellapipe_libs_drive.egg-info/not-zip-safe
artellapipe_libs_drive.egg-info/requires.txt
artellapipe_libs_drive.egg-info/top_level.txt
tests/__init__.py
tests/test_general.py