Metadata-Version: 2.1
Name: artellapipe-libs-drive
Version: 0.0.4
Summary: Library to handle Artella Project production tracking using Google Drive Sheets
Home-page: https://github.com/ArtellaPipe/artellapipe-libs-drive
Author: Tomas Poveda
Author-email: tpovedatd@gmail.com
License: MIT
Platform: UNKNOWN
Provides-Extra: dev
Provides-Extra: test
